tramp/__init__.py
tramp/_annotations.py
tramp/annotations.py
tramp/as_completed.py
tramp/async_batch_iterator.py
tramp/containers.py
tramp/modules.py
tramp/optionals.py
tramp/protected_strings.py
tramp/results.py
tramp/sentinels.py
tramp/singleton.py
tramp-0.1.17.dist-info/METADATA
tramp-0.1.17.dist-info/WHEEL
tramp-0.1.17.dist-info/RECORD
