Metadata-Version: 2.1
Name: tramp
Version: 0.1.17
Summary: A collection of utlities that can be used in other projects.
License: MIT
Author: Zech Zimmerman
Author-email: hi@zech.codes
Requires-Python: >=3.10,<4.0
Classifier: License :: OSI Approved :: MIT License
Classifier: Programming Language :: Python :: 3
Classifier: Programming Language :: Python :: 3.10
Classifier: Programming Language :: Python :: 3.11
Classifier: Programming Language :: Python :: 3.12
Classifier: Programming Language :: Python :: 3.13
